jhuki/__init__.py
jhuki/base.py
jhuki/dissipation.py
jhuki/externals/__init__.py
jhuki/externals/nrpypn/NRPyPN_shortcuts.py
jhuki/externals/nrpypn/PN_Hamiltonian_NS.py
jhuki/externals/nrpypn/PN_Hamiltonian_SO.py
jhuki/externals/nrpypn/PN_Hamiltonian_SS.py
jhuki/externals/nrpypn/PN_Hamiltonian_SSS.py
jhuki/externals/nrpypn/PN_MOmega.py
jhuki/externals/nrpypn/PN_dE_GW_dt_and_dM_dt.py
jhuki/externals/nrpypn/PN_p_r.py
jhuki/externals/nrpypn/PN_p_t.py
jhuki/externals/nrpypn/__init__.py
jhuki/externals/nrpypn/indexedexpNRPyPN.py
jhuki/grid.py
jhuki/horizons.py
jhuki/nanchecker.py
jhuki/parfile.py
jhuki/simfactory.py
jhuki/twochargedpunctures.py
jhuki/twopunctures.py
jhuki-0.1.0.dev11.dist-info/METADATA
jhuki-0.1.0.dev11.dist-info/WHEEL
jhuki-0.1.0.dev11.dist-info/RECORD
