Metadata-Version: 2.1
Name: jhuki
Version: 0.1.0.dev11
Summary: Utilities to prepare Einstein Toolkit simulations
Home-page: https://github.com/sbozzolo/Jhuki
License: GPL-3.0-or-later
Author: Gabriele Bozzola
Author-email: gabrielebozzola@arizona.edu
Requires-Python: >=3.6.2,<4.0.0
Classifier: License :: OSI Approved :: GNU General Public License v3 or later (GPLv3+)
Classifier: Programming Language :: Python :: 3
Classifier: Programming Language :: Python :: 3.7
Classifier: Programming Language :: Python :: 3.8
Classifier: Programming Language :: Python :: 3.9
Classifier: Programming Language :: Python :: 3.10
Classifier: Programming Language :: Python :: 3.11
Requires-Dist: ConfigArgParse (>=1.2.3,<2.0.0)
Requires-Dist: sympy (>=1.7.1,<2.0.0)
Project-URL: Bug Tracker, https://github.com/sbozzolo/Jhuki/issues
Project-URL: Documentation, https://sbozzolo.github.io/Jhuki
Project-URL: Repository, https://github.com/sbozzolo/Jhuki
